snips_nlu/__about__.py
snips_nlu/__init__.py
snips_nlu/__main__.py
snips_nlu/constants.py
snips_nlu/data_augmentation.py
snips_nlu/exceptions.py
snips_nlu/languages.py
snips_nlu/preprocessing.py
snips_nlu/resources.py
snips_nlu/result.py
snips_nlu/string_variations.py
snips_nlu/cli/__init__.py
snips_nlu/cli/compatibility.py
snips_nlu/cli/download.py
snips_nlu/cli/download_entity.py
snips_nlu/cli/generate_dataset.py
snips_nlu/cli/inference.py
snips_nlu/cli/link.py
snips_nlu/cli/metrics.py
snips_nlu/cli/training.py
snips_nlu/cli/utils.py
snips_nlu/cli/versions.py
snips_nlu/common/__init__.py
snips_nlu/common/abc_utils.py
snips_nlu/common/dataset_utils.py
snips_nlu/common/dict_utils.py
snips_nlu/common/from_dict.py
snips_nlu/common/io_utils.py
snips_nlu/common/log_utils.py
snips_nlu/common/registrable.py
snips_nlu/common/utils.py
snips_nlu/data/.gitignore
snips_nlu/dataset/__init__.py
snips_nlu/dataset/dataset.py
snips_nlu/dataset/entity.py
snips_nlu/dataset/intent.py
snips_nlu/dataset/utils.py
snips_nlu/dataset/validation.py
snips_nlu/dataset/yaml_wrapper.py
snips_nlu/default_configs/__init__.py
snips_nlu/default_configs/config_de.py
snips_nlu/default_configs/config_en.py
snips_nlu/default_configs/config_es.py
snips_nlu/default_configs/config_fr.py
snips_nlu/default_configs/config_it.py
snips_nlu/default_configs/config_ja.py
snips_nlu/default_configs/config_ko.py
snips_nlu/default_configs/config_pt_br.py
snips_nlu/default_configs/config_pt_pt.py
snips_nlu/entity_parser/__init__.py
snips_nlu/entity_parser/builtin_entity_parser.py
snips_nlu/entity_parser/custom_entity_parser.py
snips_nlu/entity_parser/custom_entity_parser_usage.py
snips_nlu/entity_parser/entity_parser.py
snips_nlu/intent_classifier/__init__.py
snips_nlu/intent_classifier/featurizer.py
snips_nlu/intent_classifier/intent_classifier.py
snips_nlu/intent_classifier/log_reg_classifier.py
snips_nlu/intent_classifier/log_reg_classifier_utils.py
snips_nlu/intent_parser/__init__.py
snips_nlu-0.20.2.dist-info/AUTHORS.rst
snips_nlu-0.20.2.dist-info/LICENSE
snips_nlu-0.20.2.dist-info/METADATA
snips_nlu-0.20.2.dist-info/WHEEL
snips_nlu-0.20.2.dist-info/entry_points.txt
snips_nlu-0.20.2.dist-info/top_level.txt
snips_nlu-0.20.2.dist-info/RECORD
