Metadata-Version: 2.1
Name: snips_nlu
Version: 0.20.2
Summary: Snips Natural Language Understanding library
Home-page: https://github.com/snipsco/snips-nlu
Author: Clement Doumouro, Adrien Ball
Author-email: clement.doumouro@snips.ai, adrien.ball@snips.ai
License: Apache License, Version 2.0
Project-URL: Documentation, https://snips-nlu.readthedocs.io
Project-URL: Source, https://github.com/snipsco/snips-nlu
Project-URL: Tracker, https://github.com/snipsco/snips-nlu/issues
Keywords: nlu nlp language machine learning text processing intent
Platform: UNKNOWN
Classifier: Programming Language :: Python :: 2
Classifier: Programming Language :: Python :: 2.7
Classifier: Programming Language :: Python :: 3
Classifier: Programming Language :: Python :: 3.5
Classifier: Programming Language :: Python :: 3.6
Classifier: Programming Language :: Python :: 3.7
Classifier: Programming Language :: Python :: 3.8
Classifier: Topic :: Scientific/Engineering :: Artificial Intelligence
Requires-Python: >=2.7, !=3.0.*, !=3.1.*, !=3.2.*, !=3.3.*, <4
Provides-Extra: doc
Provides-Extra: metrics
Provides-Extra: test
